[
  {
    "owner": "Thor Andreas Holberg Murtnes-Hatlestad",
    "id": "1",
    "title": "Webutvikling",
    "description": "Beskrivelse av prosjektet",
    "start_date": "25.08.2022",
    "end_date": "04.12.2022",
    "status": "planned"
  },
  {
    "owner": "Thor Andreas Holberg Murtnes-Hatlestad",
    "id": "2",
    "title": "Designmetode",
    "description": "Beskrivelse av prosjektet",
    "start_date": "25.08.2022",
    "end_date": "04.12.2022",
    "status": "ongoing"
  },
  {
    "owner": "Thor Andreas Holberg Murtnes-Hatlestad",
    "id": "3",
    "title": "Utvikling av interaktive nettsteder",
    "description": "This is the description of project 3",
    "start_date": "01.02.2022",
    "end_date": "31.02.2023",
    "status": "completed"
  }
]
